modeltasks/__init__.py
modeltasks/config.py
modeltasks/data.py
modeltasks/log.py
modeltasks/registry.py
modeltasks/task.py
modeltasks/handler/__init__.py
modeltasks/handler/abstract.py
modeltasks/scheduler/__init__.py
modeltasks/scheduler/abstract.py
modeltasks/scheduler/asynchronous.py
modeltasks/scheduler/job.py
modeltasks/scheduler/multiprocessing.py
modeltasks/scheduler/remote.py
modeltasks/scheduler/thread.py
modeltasks/util/__init__.py
modeltasks/util/hash.py
modeltasks/util/io.py
modeltasks/util/network.py
modeltasks/util/serializer.py
modeltasks/util/task.py
modeltasks-0.1.20.dist-info/METADATA
modeltasks-0.1.20.dist-info/WHEEL
modeltasks-0.1.20.dist-info/top_level.txt
modeltasks-0.1.20.dist-info/RECORD
