Metadata-Version: 2.2
Name: modeltasks
Version: 0.1.20
Summary: A lightweight workflow management system and task graph
Home-page: https://gitlab.com/geotom/modeltasks
Author: Thomas Wanderer
Author-email: contact-project+geotom-modeltasks-support@incoming.gitlab.com
License: MIT
Keywords: Tasks,Model,DAG,Graph,Model,Processing,Workflow management
Classifier: Development Status :: 3 - Alpha
Classifier: Intended Audience :: Developers
Classifier: Intended Audience :: Science/Research
Classifier: Topic :: Software Development
Classifier: License :: OSI Approved :: MIT License
Classifier: Programming Language :: Python :: 3
Classifier: Programming Language :: Python :: 3.10
Requires-Dist: networkx
Requires-Dist: matplotlib
Requires-Dist: python-dotenv
Dynamic: author
Dynamic: author-email
Dynamic: classifier
Dynamic: description
Dynamic: description-content-type
Dynamic: home-page
Dynamic: keywords
Dynamic: license
Dynamic: requires-dist
Dynamic: summary
